{
  "legendarysurvivaloverhaul:main/root": {
    "criteria": {
      "main": "2026-01-15 20:20:30 +0700"
    },
    "done": true
  },
  "minecraft:recipes/decorations/crafting_table": {
    "criteria": {
      "unlock_right_away": "2026-01-15 20:20:30 +0700"
    },
    "done": true
  },
  "deceasedcraft:exploration": {
    "criteria": {
      "deceasedcraft_startup": "2026-01-15 20:20:30 +0700"
    },
    "done": true
  },
  "undead_revamp2:theundeadchallenges": {
    "criteria": {
      "theundeadchallenges": "2026-01-15 20:20:30 +0700"
    },
    "done": true
  },
  "lootr:root": {
    "criteria": {
      "always_true": "2026-01-15 20:20:30 +0700"
    },
    "done": true
  },
  "storagedrawers:recipes/storagedrawers/one_stack_upgrade": {
    "criteria": {
      "has_template": "2026-01-15 20:20:31 +0700"
    },
    "done": true
  },
  "create:root": {
    "criteria": {
      "0": "2026-01-15 20:20:31 +0700"
    },
    "done": true
  },
  "naturalist:recipes/food/cooked_egg": {
    "criteria": {
      "has_eggs": "2026-01-15 20:20:31 +0700"
    },
    "done": true
  },
  "storagedrawers:recipes/storagedrawers/illumination_upgrade": {
    "criteria": {
      "has_template": "2026-01-15 20:20:31 +0700"
    },
    "done": true
  },
  "storagedrawers:recipes/storagedrawers/remote_upgrade": {
    "criteria": {
      "has_template": "2026-01-15 20:20:31 +0700"
    },
    "done": true
  },
  "solcarrot:recipes/food_book": {
    "criteria": {
      "has_book": "2026-01-15 20:20:31 +0700",
      "has_carrot": "2026-01-15 20:20:31 +0700"
    },
    "done": true
  },
  "storagedrawers:recipes/storagedrawers/personal_key_cofh": {
    "criteria": {
      "has_template": "2026-01-15 20:20:31 +0700"
    },
    "done": true
  },
  "mapperbase:recipes/mapperbase_group/steel_ingot": {
    "criteria": {
      "has_raw_steel": "2026-01-15 20:20:31 +0700"
    },
    "done": true
  },
  "storagedrawers:recipes/storagedrawers/acacia_trim": {
    "criteria": {
      "has_planks": "2026-01-15 20:20:31 +0700"
    },
    "done": true
  },
  "storagedrawers:recipes/storagedrawers/priority_key": {
    "criteria": {
      "has_template": "2026-01-15 20:20:31 +0700"
    },
    "done": true
  },
  "storagedrawers:recipes/storagedrawers/cherry_trim": {
    "criteria": {
      "has_planks": "2026-01-15 20:20:31 +0700"
    },
    "done": true
  },
  "storagedrawers:recipes/storagedrawers/gold_storage_upgrade": {
    "criteria": {
      "has_template": "2026-01-15 20:20:31 +0700"
    },
    "done": true
  },
  "storagedrawers:recipes/storagedrawers/birch_trim": {
    "criteria": {
      "has_planks": "2026-01-15 20:20:31 +0700"
    },
    "done": true
  },
  "storagedrawers:recipes/storagedrawers/void_upgrade": {
    "criteria": {
      "has_template": "2026-01-15 20:20:31 +0700"
    },
    "done": true
  },
  "storagedrawers:recipes/storagedrawers/fill_level_upgrade": {
    "criteria": {
      "has_template": "2026-01-15 20:20:31 +0700"
    },
    "done": true
  },
  "vinery:main/root": {
    "criteria": {
      "seeds": "2026-01-15 20:20:31 +0700"
    },
    "done": true
  },
  "storagedrawers:recipes/storagedrawers/oak_trim": {
    "criteria": {
      "has_planks": "2026-01-15 20:20:31 +0700"
    },
    "done": true
  },
  "storagedrawers:recipes/storagedrawers/emerald_storage_upgrade": {
    "criteria": {
      "has_template": "2026-01-15 20:20:31 +0700"
    },
    "done": true
  },
  "storagedrawers:recipes/storagedrawers/obsidian_storage_upgrade": {
    "criteria": {
      "has_template": "2026-01-15 20:20:31 +0700"
    },
    "done": true
  },
  "storagedrawers:recipes/storagedrawers/iron_storage_upgrade": {
    "criteria": {
      "has_template": "2026-01-15 20:20:31 +0700"
    },
    "done": true
  },
  "storagedrawers:recipes/storagedrawers/diamond_storage_upgrade": {
    "criteria": {
      "has_template": "2026-01-15 20:20:31 +0700"
    },
    "done": true
  },
  "storagedrawers:recipes/storagedrawers/remote_group_upgrade": {
    "criteria": {
      "has_template": "2026-01-15 20:20:31 +0700"
    },
    "done": true
  },
  "storagedrawers:recipes/storagedrawers/drawer_puller": {
    "criteria": {
      "has_template": "2026-01-15 20:20:31 +0700"
    },
    "done": true
  },
  "storagedrawers:recipes/storagedrawers/crimson_trim": {
    "criteria": {
      "has_planks": "2026-01-15 20:20:31 +0700"
    },
    "done": true
  },
  "deceasedcraft:building/suburb_residential/building_residentiala": {
    "criteria": {
      "building_residentiala": "2026-01-15 20:20:31 +0700"
    },
    "done": true
  },
  "storagedrawers:recipes/storagedrawers/shroud_key": {
    "criteria": {
      "has_template": "2026-01-15 20:20:31 +0700"
    },
    "done": true
  },
  "storagedrawers:recipes/storagedrawers/portability_upgrade": {
    "criteria": {
      "has_template": "2026-01-15 20:20:31 +0700"
    },
    "done": true
  },
  "bakery:main/root": {
    "criteria": {
      "seeds": "2026-01-15 20:20:31 +0700"
    },
    "done": true
  },
  "storagedrawers:recipes/storagedrawers/drawer_key": {
    "criteria": {
      "has_template": "2026-01-15 20:20:31 +0700"
    },
    "done": true
  },
  "storagedrawers:recipes/storagedrawers/min_redstone_upgrade": {
    "criteria": {
      "has_template": "2026-01-15 20:20:31 +0700"
    },
    "done": true
  },
  "storagedrawers:recipes/storagedrawers/keyring": {
    "criteria": {
      "has_template": "2026-01-15 20:20:31 +0700"
    },
    "done": true
  },
  "storagedrawers:recipes/storagedrawers/personal_key": {
    "criteria": {
      "has_template": "2026-01-15 20:20:31 +0700"
    },
    "done": true
  },
  "storagedrawers:recipes/storagedrawers/warped_trim": {
    "criteria": {
      "has_planks": "2026-01-15 20:20:31 +0700"
    },
    "done": true
  },
  "storagedrawers:recipes/storagedrawers/jungle_trim": {
    "criteria": {
      "has_planks": "2026-01-15 20:20:31 +0700"
    },
    "done": true
  },
  "storagedrawers:recipes/storagedrawers/max_redstone_upgrade": {
    "criteria": {
      "has_template": "2026-01-15 20:20:31 +0700"
    },
    "done": true
  },
  "storagedrawers:recipes/storagedrawers/bamboo_trim": {
    "criteria": {
      "has_planks": "2026-01-15 20:20:31 +0700"
    },
    "done": true
  },
  "storagedrawers:recipes/storagedrawers/mangrove_trim": {
    "criteria": {
      "has_planks": "2026-01-15 20:20:31 +0700"
    },
    "done": true
  },
  "storagedrawers:recipes/storagedrawers/redstone_upgrade": {
    "criteria": {
      "has_template": "2026-01-15 20:20:31 +0700"
    },
    "done": true
  },
  "storagedrawers:recipes/storagedrawers/spruce_trim": {
    "criteria": {
      "has_planks": "2026-01-15 20:20:31 +0700"
    },
    "done": true
  },
  "farmersdelight:main/root": {
    "criteria": {
      "seeds": "2026-01-15 20:20:31 +0700"
    },
    "done": true
  },
  "storagedrawers:recipes/storagedrawers/quantify_key": {
    "criteria": {
      "has_template": "2026-01-15 20:20:31 +0700"
    },
    "done": true
  },
  "storagedrawers:recipes/storagedrawers/dark_oak_trim": {
    "criteria": {
      "has_planks": "2026-01-15 20:20:31 +0700"
    },
    "done": true
  },
  "storagedrawers:recipes/storagedrawers/balance_fill_upgrade": {
    "criteria": {
      "has_template": "2026-01-15 20:20:31 +0700"
    },
    "done": true
  },
  "legendarysurvivaloverhaul:recipes/misc/morphine": {
    "criteria": {
      "has_plaster": "2026-01-15 20:20:32 +0700"
    },
    "done": true
  },
  "legendarysurvivaloverhaul:recipes/misc/bandage": {
    "criteria": {
      "has_plaster": "2026-01-15 20:20:32 +0700"
    },
    "done": true
  },
  "refurbished_furniture:recipes/misc/slicing/bread_slice_from_bread": {
    "criteria": {
      "has_bread": "2026-01-15 20:20:32 +0700"
    },
    "done": true
  },
  "bakery:recipes/sandwich": {
    "criteria": {
      "has_bread": "2026-01-15 20:20:32 +0700"
    },
    "done": true
  },
  "biomesoplenty:biomesoplenty/root": {
    "criteria": {
      "shrubland": "2026-01-15 20:20:33 +0700"
    },
    "done": true
  },
  "biomesoplenty:biomesoplenty/all_biomes": {
    "criteria": {
      "shrubland": "2026-01-15 20:20:33 +0700",
      "grassland": "2026-01-21 23:15:20 +0700"
    },
    "done": false
  },
  "minecraft:recipes/redstone/tripwire_hook": {
    "criteria": {
      "has_string": "2026-01-15 20:20:47 +0700"
    },
    "done": true
  },
  "minecraft:recipes/decorations/candle": {
    "criteria": {
      "has_string": "2026-01-15 20:20:47 +0700"
    },
    "done": true
  },
  "refurbished_furniture:recipes/misc/constructing/magenta_trampoline": {
    "criteria": {
      "has_string": "2026-01-15 20:20:47 +0700"
    },
    "done": true
  },
  "minecraft:recipes/combat/bow": {
    "criteria": {
      "has_string": "2026-01-15 20:20:47 +0700"
    },
    "done": true
  },
  "refurbished_furniture:recipes/misc/constructing/light_gray_trampoline": {
    "criteria": {
      "has_string": "2026-01-15 20:20:47 +0700"
    },
    "done": true
  },
  "refurbished_furniture:recipes/misc/constructing/green_trampoline": {
    "criteria": {
      "has_string": "2026-01-15 20:20:47 +0700"
    },
    "done": true
  },
  "refurbished_furniture:recipes/misc/knife": {
    "criteria": {
      "has_string": "2026-01-15 20:20:47 +0700"
    },
    "done": true
  },
  "refurbished_furniture:recipes/misc/wrench": {
    "criteria": {
      "has_string": "2026-01-15 20:20:47 +0700"
    },
    "done": true
  },
  "refurbished_furniture:recipes/misc/constructing/pink_trampoline": {
    "criteria": {
      "has_string": "2026-01-15 20:20:47 +0700"
    },
    "done": true
  },
  "refurbished_furniture:recipes/misc/spatula": {
    "criteria": {
      "has_string": "2026-01-15 20:20:47 +0700"
    },
    "done": true
  },
  "refurbished_furniture:recipes/misc/constructing/orange_trampoline": {
    "criteria": {
      "has_string": "2026-01-15 20:20:47 +0700"
    },
    "done": true
  },
  "refurbished_furniture:recipes/misc/constructing/cyan_trampoline": {
    "criteria": {
      "has_string": "2026-01-15 20:20:47 +0700"
    },
    "done": true
  },
  "refurbished_furniture:recipes/misc/constructing/brown_trampoline": {
    "criteria": {
      "has_string": "2026-01-15 20:20:47 +0700"
    },
    "done": true
  },
  "refurbished_furniture:recipes/misc/constructing/light_blue_trampoline": {
    "criteria": {
      "has_string": "2026-01-15 20:20:47 +0700"
    },
    "done": true
  },
  "refurbished_furniture:recipes/misc/constructing/red_trampoline": {
    "criteria": {
      "has_string": "2026-01-15 20:20:47 +0700"
    },
    "done": true
  },
  "refurbished_furniture:recipes/misc/constructing/blue_trampoline": {
    "criteria": {
      "has_string": "2026-01-15 20:20:47 +0700"
    },
    "done": true
  },
  "refurbished_furniture:recipes/misc/constructing/white_trampoline": {
    "criteria": {
      "has_string": "2026-01-15 20:20:47 +0700"
    },
    "done": true
  },
  "minecraft:adventure/root": {
    "criteria": {
      "killed_something": "2026-01-15 20:20:47 +0700"
    },
    "done": true
  },
  "minecraft:recipes/combat/crossbow": {
    "criteria": {
      "has_string": "2026-01-15 20:20:47 +0700"
    },
    "done": true
  },
  "refurbished_furniture:recipes/misc/constructing/yellow_trampoline": {
    "criteria": {
      "has_string": "2026-01-15 20:20:47 +0700"
    },
    "done": true
  },
  "refurbished_furniture:recipes/misc/constructing/gray_trampoline": {
    "criteria": {
      "has_string": "2026-01-15 20:20:47 +0700"
    },
    "done": true
  },
  "minecraft:recipes/tools/fishing_rod": {
    "criteria": {
      "has_string": "2026-01-15 20:20:47 +0700"
    },
    "done": true
  },
  "refurbished_furniture:recipes/misc/constructing/lime_trampoline": {
    "criteria": {
      "has_string": "2026-01-15 20:20:47 +0700"
    },
    "done": true
  },
  "refurbished_furniture:recipes/misc/constructing/black_trampoline": {
    "criteria": {
      "has_string": "2026-01-15 20:20:47 +0700"
    },
    "done": true
  },
  "minecraft:recipes/building_blocks/white_wool_from_string": {
    "criteria": {
      "has_string": "2026-01-15 20:20:47 +0700"
    },
    "done": true
  },
  "refurbished_furniture:recipes/misc/constructing/purple_trampoline": {
    "criteria": {
      "has_string": "2026-01-15 20:20:47 +0700"
    },
    "done": true
  },
  "minecraft:recipes/decorations/loom": {
    "criteria": {
      "has_string": "2026-01-15 20:20:47 +0700"
    },
    "done": true
  },
  "minecraft:adventure/kill_a_mob": {
    "criteria": {
      "minecraft:zombie": "2026-01-15 20:20:56 +0700"
    },
    "done": true
  },
  "minecraft:adventure/kill_all_mobs": {
    "criteria": {
      "minecraft:husk": "2026-01-15 20:21:29 +0700",
      "minecraft:zombie": "2026-01-15 20:20:56 +0700"
    },
    "done": false
  },
  "deceasedcraft:large_building/suburb_residential/multi_residentialf": {
    "criteria": {
      "multi_residentialf": "2026-01-15 20:21:42 +0700"
    },
    "done": true
  },
  "refurbished_furniture:recipes/misc/slicing/bone_meal_from_bone": {
    "criteria": {
      "has_bone": "2026-01-15 20:21:53 +0700"
    },
    "done": true
  },
  "minecraft:recipes/misc/bone_meal": {
    "criteria": {
      "has_bone": "2026-01-15 20:21:53 +0700"
    },
    "done": true
  },
  "farmersdelight:recipes/cooking/bone_broth": {
    "criteria": {
      "has_bone": "2026-01-15 20:21:53 +0700"
    },
    "done": true
  },
  "create:recipes/building_blocks/polished_cut_calcite_stairs_from_stone_types_calcite_stonecutting": {
    "criteria": {
      "has_stone_types_calcite": "2026-01-15 20:22:13 +0700"
    },
    "done": true
  },
  "create:recipes/building_blocks/small_calcite_brick_stairs_from_stone_types_calcite_stonecutting": {
    "criteria": {
      "has_stone_types_calcite": "2026-01-15 20:22:13 +0700"
    },
    "done": true
  },
  "create:recipes/building_blocks/cut_calcite_stairs": {
    "criteria": {
      "has_cut_calcite": "2026-01-15 20:22:13 +0700"
    },
    "done": true
  },
  "create:recipes/building_blocks/calcite_pillar_from_stone_types_calcite_stonecutting": {
    "criteria": {
      "has_stone_types_calcite": "2026-01-15 20:22:13 +0700"
    },
    "done": true
  },
  "create:recipes/building_blocks/cut_calcite_wall": {
    "criteria": {
      "has_cut_calcite": "2026-01-15 20:22:13 +0700"
    },
    "done": true
  },
  "create:recipes/building_blocks/cut_calcite_slab_from_stone_types_calcite_stonecutting": {
    "criteria": {
      "has_stone_types_calcite": "2026-01-15 20:22:13 +0700"
    },
    "done": true
  },
  "create:recipes/building_blocks/polished_cut_calcite_slab_from_stone_types_calcite_stonecutting": {
    "criteria": {
      "has_stone_types_calcite": "2026-01-15 20:22:13 +0700"
    },
    "done": true
  },
  "create:recipes/building_blocks/cut_calcite_from_stone_types_calcite_stonecutting": {
    "criteria": {
      "has_stone_types_calcite": "2026-01-15 20:22:13 +0700"
    },
    "done": true
  },
  "create:recipes/building_blocks/cut_calcite_stairs_from_stone_types_calcite_stonecutting": {
    "criteria": {
      "has_stone_types_calcite": "2026-01-15 20:22:13 +0700"
    },
    "done": true
  },
  "create:recipes/building_blocks/small_calcite_bricks_from_stone_types_calcite_stonecutting": {
    "criteria": {
      "has_stone_types_calcite": "2026-01-15 20:22:13 +0700"
    },
    "done": true
  },
  "create:recipes/building_blocks/cut_calcite_brick_wall_from_stone_types_calcite_stonecutting": {
    "criteria": {
      "has_stone_types_calcite": "2026-01-15 20:22:13 +0700"
    },
    "done": true
  },
  "create:recipes/building_blocks/small_calcite_brick_wall_from_stone_types_calcite_stonecutting": {
    "criteria": {
      "has_stone_types_calcite": "2026-01-15 20:22:13 +0700"
    },
    "done": true
  },
  "create:recipes/building_blocks/cut_calcite_bricks_from_stone_types_calcite_stonecutting": {
    "criteria": {
      "has_stone_types_calcite": "2026-01-15 20:22:13 +0700"
    },
    "done": true
  },
  "create:recipes/building_blocks/layered_calcite_from_stone_types_calcite_stonecutting": {
    "criteria": {
      "has_stone_types_calcite": "2026-01-15 20:22:13 +0700"
    },
    "done": true
  },
  "create:recipes/building_blocks/cut_calcite_wall_from_stone_types_calcite_stonecutting": {
    "criteria": {
      "has_stone_types_calcite": "2026-01-15 20:22:13 +0700"
    },
    "done": true
  },
  "create:recipes/building_blocks/polished_cut_calcite_from_stone_types_calcite_stonecutting": {
    "criteria": {
      "has_stone_types_calcite": "2026-01-15 20:22:13 +0700"
    },
    "done": true
  },
  "create:recipes/building_blocks/small_calcite_brick_slab_from_stone_types_calcite_stonecutting": {
    "criteria": {
      "has_stone_types_calcite": "2026-01-15 20:22:13 +0700"
    },
    "done": true
  },
  "create:recipes/building_blocks/cut_calcite_brick_slab_from_stone_types_calcite_stonecutting": {
    "criteria": {
      "has_stone_types_calcite": "2026-01-15 20:22:13 +0700"
    },
    "done": true
  },
  "create:recipes/building_blocks/polished_cut_calcite_wall_from_stone_types_calcite_stonecutting": {
    "criteria": {
      "has_stone_types_calcite": "2026-01-15 20:22:13 +0700"
    },
    "done": true
  },
  "create:recipes/building_blocks/cut_calcite_slab": {
    "criteria": {
      "has_cut_calcite": "2026-01-15 20:22:13 +0700"
    },
    "done": true
  },
  "create:recipes/building_blocks/calcite_from_stone_types_calcite_stonecutting": {
    "criteria": {
      "has_stone_types_calcite": "2026-01-15 20:22:13 +0700"
    },
    "done": true
  },
  "create:recipes/building_blocks/cut_calcite_brick_stairs_from_stone_types_calcite_stonecutting": {
    "criteria": {
      "has_stone_types_calcite": "2026-01-15 20:22:13 +0700"
    },
    "done": true
  },
  "deceasedcraft:large_building/suburb_residential/multi_residentialsurvivor": {
    "criteria": {
      "multi_residentialsurvivor": "2026-01-15 20:22:49 +0700"
    },
    "done": true
  },
  "minecraft:husbandry/balanced_diet": {
    "criteria": {
      "bread": "2026-01-15 20:23:26 +0700"
    },
    "done": false
  },
  "minecraft:husbandry/root": {
    "criteria": {
      "consumed_item": "2026-01-15 20:23:26 +0700"
    },
    "done": true
  },
  "deceasedcraft:building/suburb_residential/building_residentialc": {
    "criteria": {
      "building_residentialc": "2026-01-21 23:15:20 +0700"
    },
    "done": true
  },
  "deceasedcraft:large_building/suburb_residential/multi_policestation": {
    "criteria": {
      "multi_policestation": "2026-01-21 23:16:15 +0700"
    },
    "done": true
  },
  "DataVersion": 3465
}